arc/__init__.py
arc/core/__init__.py
arc/core/arc.py
arc/core/datasets.py
arc/core/main.py
arc/core/utils.py
arc/torch/__init__.py
arc/torch/test.py
arc_agi-0.3.0.dist-info/METADATA
arc_agi-0.3.0.dist-info/WHEEL
arc_agi-0.3.0.dist-info/entry_points.txt
arc_agi-0.3.0.dist-info/licenses/LICENSE
arc_agi-0.3.0.dist-info/RECORD
